psg_reskinner/__init__.py
psg_reskinner/__main__.py
psg_reskinner/colorprocessor.py
psg_reskinner/constants.py
psg_reskinner/default.py
psg_reskinner/deprecation.py
psg_reskinner/easings.py
psg_reskinner/exception.py
psg_reskinner/psg_reskinner.py
psg_reskinner/utilities.py
psg_reskinner/version.py
psg_reskinner-3.1.0.dist-info/LICENSE
psg_reskinner-3.1.0.dist-info/METADATA
psg_reskinner-3.1.0.dist-info/WHEEL
psg_reskinner-3.1.0.dist-info/top_level.txt
psg_reskinner-3.1.0.dist-info/RECORD
