Metadata-Version: 2.1
Name: psg-reskinner
Version: 3.1.0
Summary: Instantaneous theme changing for PySimpleGUI windows.
Author-email: "Divine U. Afam-Ifediogor" <divineafam@gmail.com>
License: MIT License
Project-URL: Homepage, https://github.com/definite-d/psg_reskinner/
Project-URL: Bug Tracker, https://github.com/definite-d/psg_reskinner/issues/
Keywords: PySimpleGUI,reskin,realtime,theme,color
Classifier: License :: OSI Approved :: MIT License
Classifier: Programming Language :: Python
Classifier: Programming Language :: Python :: 3
Classifier: Programming Language :: Python :: 3.7
Requires-Python: >=3.7
License-File: LICENSE
Requires-Dist: colour >=0.1.5
Requires-Dist: PySimpleGUI >=4.60.3.96
